setup.py
deployer/__init__.py
deployer/cli.py
deployer/client.py
deployer/console.py
deployer/daemonize.py
deployer/exceptions.py
deployer/groups.py
deployer/host_container.py
deployer/options.py
deployer/pseudo_terminal.py
deployer/query.py
deployer/scp_shell.py
deployer/shell.py
deployer/std.py
deployer.egg-info/PKG-INFO
deployer.egg-info/SOURCES.txt
deployer.egg-info/dependency_links.txt
deployer.egg-info/requires.txt
deployer.egg-info/top_level.txt
deployer/contrib/__init__.py
deployer/contrib/commands.py
deployer/contrib/default_config.py
deployer/contrib/loggers/__init__.py
deployer/contrib/loggers/on_host.py
deployer/contrib/nodes/__init__.py
deployer/contrib/nodes/apt_get.py
deployer/contrib/nodes/config.py
deployer/contrib/nodes/connect.py
deployer/contrib/nodes/cron.py
deployer/contrib/nodes/django.py
deployer/contrib/nodes/git.py
deployer/contrib/nodes/hg.py
deployer/contrib/nodes/inspection.py
deployer/contrib/nodes/monitoring.py
deployer/contrib/nodes/mysql.py
deployer/contrib/nodes/redis.py
deployer/contrib/nodes/sysvinit.py
deployer/contrib/nodes/tmux.py
deployer/contrib/nodes/upstart.py
deployer/contrib/nodes/users.py
deployer/contrib/nodes/utils.py
deployer/contrib/nodes/uwsgi.py
deployer/contrib/nodes/variants.py
deployer/contrib/nodes/virtualenv.py
deployer/contrib/unittest/__init__.py
deployer/contrib/unittest/nodes/__init__.py
deployer/host/__init__.py
deployer/host/base.py
deployer/host/local.py
deployer/host/paramiko_connect_patch.py
deployer/host/ssh.py
deployer/host/vagrant.py
deployer/inspection/__init__.py
deployer/inspection/filters.py
deployer/inspection/inspector.py
deployer/loggers/__init__.py
deployer/loggers/default.py
deployer/loggers/trace.py
deployer/node/__init__.py
deployer/node/base.py
deployer/node/decorators.py
deployer/node/role_mapping.py
deployer/run/__init__.py
deployer/run/ipython_shell.py
deployer/run/socket_client.py
deployer/run/socket_server.py
deployer/run/standalone_shell.py
deployer/run/telnet_server.py
deployer/utils/__init__.py
deployer/utils/network.py
deployer/utils/string_utils.py
tests/__init__.py
tests/console_test.py
tests/default_config_test.py
