Metadata-Version: 1.1
Name: deployer
Version: 0.3.6
Summary: Library for automating system deployments
Home-page: https://github.com/jonathanslenders/python-deployer
Author: Jonathan Slenders, Mobile Vikings, City Live nv
Author-email: jonathan.slenders@mobilevikings.com
License: LICENSE.txt
Platform: UNKNOWN
Classifier: Development Status :: 5 - Production/Stable
Classifier: Environment :: Console
Classifier: Intended Audience :: System Administrators
Classifier: Operating System :: POSIX
Classifier: Programming Language :: Python
Classifier: Topic :: System :: Installation/Setup
Classifier: Topic :: System :: Shells
